{
  "GroupGUID": "0abc5d0e-d95c-4516-85c9-469ca0d4d88c",
  "GroupName": "DefaultData",
  "ConfigPrefabPath": null,
  "LevelGraph": null,
  "Model": null,
  "AreaAnchorName": "LevelArea_P30120_F30120001_G1",
  "SaveType": "Temporary",
  "CheckClearMainMissionID": 0,
  "UnlockMainMissionID": 0,
  "AnchorList": [
    {
      "Name": "Anchor1",
      "RotY": 0.0,
      "Comment": null,
      "ID": 1,
      "PosX": 39.25,
      "PosY": 3.942143,
      "PosZ": 227.75,
      "IsDelete": false
    }
  ],
  "ModelList": [],
  "MonsterList": [],
  "PropList": [],
  "WaypointList": [],
  "PathwayList": [],
  "BattleAreaList": [
    {
      "EnviroProfile": null,
      "Tags": [
        "BattleArea01"
      ],
      "Name": "BattleArea1",
      "RotY": 271.69,
      "Comment": null,
      "ID": 1,
      "PosX": 1235.5,
      "PosY": 0.0,
      "PosZ": -1593.2,
      "IsDelete": false
    }
  ],
  "NPCList": [],
  "GroupRefreshID": 0,
  "RandomNPCMonsterList": null,
  "InitialRandomNPCMonsterIDList": null
}