{
  "GroupGUID": "78c042c2-355b-4b34-9247-b1922c7ca27f",
  "GroupName": "MinePillar",
  "ConfigPrefabPath": null,
  "LevelGraph": "Config/Level/Maze/MazeExtra/Puzzle/M2-2/Maze_Prop_3xRangedAll_M22_Puzzle_Group.json",
  "Model": null,
  "AreaAnchorName": "LevelArea_P20122_F20122001_G23",
  "SaveType": "Temporary",
  "CheckClearMainMissionID": 0,
  "UnlockMainMissionID": 0,
  "AnchorList": [],
  "ModelList": [],
  "MonsterList": [],
  "PropList": [
    {
      "RotX": 0.0,
      "RotZ": 0.0,
      "PropID": 202,
      "IsLimitedLife": false,
      "LifeTime": 0.0,
      "InitLevelGraph": null,
      "Trigger": null,
      "CreateOnInitial": true,
      "ValueSource": null,
      "CampID": 0,
      "State": "Closed",
      "RecordID": 0,
      "EventID": 0,
      "AnchorGroupID": 0,
      "AnchorID": 0,
      "MapTeleportID": 0,
      "ChestID": 0,
      "DialogueTriggerAngle": 0,
      "DialogueGroups": [],
      "OverrideTriggerHint": false,
      "HintRange": 0.0,
      "ServerInteractVerificationIDList": [],
      "StageObjectCapture": null,
      "Name": "Prop1",
      "RotY": 0.0,
      "Comment": null,
      "ID": 300001,
      "PosX": 22.234,
      "PosY": 22.18545,
      "PosZ": 127.978,
      "IsDelete": false
    },
    {
      "RotX": 0.0,
      "RotZ": 0.0,
      "PropID": 203,
      "IsLimitedLife": false,
      "LifeTime": 0.0,
      "InitLevelGraph": "Config/Level/Maze/MazeProp/Maze_Prop_Element_Pillar_Hit_2-2_2.json",
      "Trigger": null,
      "CreateOnInitial": true,
      "ValueSource": null,
      "CampID": 0,
      "State": "Closed",
      "RecordID": 0,
      "EventID": 0,
      "AnchorGroupID": 0,
      "AnchorID": 0,
      "MapTeleportID": 0,
      "ChestID": 0,
      "DialogueTriggerAngle": 0,
      "DialogueGroups": [],
      "OverrideTriggerHint": false,
      "HintRange": 0.0,
      "ServerInteractVerificationIDList": [],
      "StageObjectCapture": null,
      "Name": "Prop2",
      "RotY": 0.0,
      "Comment": null,
      "ID": 300002,
      "PosX": 24.28,
      "PosY": 25.09118,
      "PosZ": 155.19,
      "IsDelete": false
    },
    {
      "RotX": 0.0,
      "RotZ": 0.0,
      "PropID": 202,
      "IsLimitedLife": false,
      "LifeTime": 0.0,
      "InitLevelGraph": "Config/Level/Maze/MazeProp/Maze_Prop_Element_Pillar_Hit_2-2_3.json",
      "Trigger": null,
      "CreateOnInitial": true,
      "ValueSource": null,
      "CampID": 0,
      "State": "Closed",
      "RecordID": 0,
      "EventID": 0,
      "AnchorGroupID": 0,
      "AnchorID": 0,
      "MapTeleportID": 0,
      "ChestID": 0,
      "DialogueTriggerAngle": 0,
      "DialogueGroups": [],
      "OverrideTriggerHint": false,
      "HintRange": 0.0,
      "ServerInteractVerificationIDList": [],
      "StageObjectCapture": null,
      "Name": "Prop3",
      "RotY": 0.0,
      "Comment": null,
      "ID": 300003,
      "PosX": 28.23,
      "PosY": 25.07823,
      "PosZ": 169.75,
      "IsDelete": false
    },
    {
      "RotX": 0.0,
      "RotZ": 0.0,
      "PropID": 100,
      "IsLimitedLife": false,
      "LifeTime": 0.0,
      "InitLevelGraph": "Config/Level/Maze/MazeExtra/Puzzle/M2-2/Maze_Prop_3xRangedAll_M22_Puzzle_Camera.json",
      "Trigger": null,
      "CreateOnInitial": true,
      "ValueSource": null,
      "CampID": 0,
      "State": "Closed",
      "RecordID": 0,
      "EventID": 0,
      "AnchorGroupID": 0,
      "AnchorID": 0,
      "MapTeleportID": 0,
      "ChestID": 0,
      "DialogueTriggerAngle": 120,
      "DialogueGroups": [],
      "OverrideTriggerHint": false,
      "HintRange": 0.0,
      "ServerInteractVerificationIDList": [],
      "StageObjectCapture": null,
      "Name": "Prop4",
      "RotY": 0.0,
      "Comment": "镜头控制",
      "ID": 300004,
      "PosX": 0.0,
      "PosY": 0.0,
      "PosZ": 0.0,
      "IsDelete": false
    }
  ],
  "WaypointList": [],
  "PathwayList": [],
  "BattleAreaList": [],
  "NPCList": [],
  "GroupRefreshID": 1,
  "RandomNPCMonsterList": null,
  "InitialRandomNPCMonsterIDList": null
}